fmlc/__init__.py
fmlc/baseclasses.py
fmlc/stackedclasses.py
fmlc/triggering.py
fmlc/utility.py
fmlc/pythonDB/__init__.py
fmlc/pythonDB/pythonDB.py
fmlc/pythonDB/utility.py
FMLC-1.3.2.dist-info/METADATA
FMLC-1.3.2.dist-info/WHEEL
FMLC-1.3.2.dist-info/license.txt
FMLC-1.3.2.dist-info/top_level.txt
FMLC-1.3.2.dist-info/RECORD
