Metadata-Version: 2.1
Name: FMLC
Version: 1.3.2
Summary: A framework/backend for multi-layer and multi-time domain controller.
Home-page: https://github.com/LBNL-ETA/FMLC
Author: Gehbauer, Christoph
Project-URL: Bug Tracker, https://github.com/LBNL-ETA/FMLC/issues
Classifier: Programming Language :: Python :: 3
Classifier: Operating System :: OS Independent
Requires-Python: >=3.6
License-File: license.txt
Requires-Dist: pandas
Requires-Dist: requests
Requires-Dist: numpy
